{
  "main": {
    "id": "c62e599a04601b4d",
    "type": "split",
    "children": [
      {
        "id": "2ded25ac7279f695",
        "type": "tabs",
        "children": [
          {
            "id": "c15ca8b08b6f374b",
            "type": "leaf",
            "state": {
              "type": "markdown",
              "state": {
                "file": "_posts/Blog/Todo/2024-05-06-ToDo.md",
                "mode": "source",
                "source": true
              }
            }
          }
        ]
      }
    ],
    "direction": "vertical"
  },
  "left": {
    "id": "699873e72a36232f",
    "type": "split",
    "children": [
      {
        "id": "95e2c06c5fb4ec9e",
        "type": "tabs",
        "children": [
          {
            "id": "193004c8919e2383",
            "type": "leaf",
            "state": {
              "type": "recent-files",
              "state": {}
            }
          },
          {
            "id": "7a96a7b6ca269dce",
            "type": "leaf",
            "state": {
              "type": "file-explorer",
              "state": {
                "sortOrder": "alphabetical"
              }
            }
          },
          {
            "id": "47175694c91b20be",
            "type": "leaf",
            "state": {
              "type": "search",
              "state": {
                "query": "逆行列",
                "matchingCase": false,
                "explainSearch": false,
                "collapseAll": false,
                "extraContext": false,
                "sortOrder": "alphabetical"
              }
            }
          },
          {
            "id": "4e2bd817cc223591",
            "type": "leaf",
            "state": {
              "type": "bookmarks",
              "state": {}
            }
          }
        ],
        "currentTab": 1
      }
    ],
    "direction": "horizontal",
    "width": 200,
    "collapsed": true
  },
  "right": {
    "id": "c28fa44957b113d7",
    "type": "split",
    "children": [
      {
        "id": "06f2c44063a449fa",
        "type": "tabs",
        "children": [
          {
            "id": "c00359485fd6c205",
            "type": "leaf",
            "state": {
              "type": "outline",
              "state": {
                "file": "_posts/Blog/Todo/2024-05-06-ToDo.md"
              }
            }
          },
          {
            "id": "d299e6c63c1dc844",
            "type": "leaf",
            "state": {
              "type": "tag",
              "state": {
                "sortOrder": "frequency",
                "useHierarchy": true
              }
            }
          },
          {
            "id": "c86536808d07252c",
            "type": "leaf",
            "state": {
              "type": "backlink",
              "state": {
                "file": "_posts/Blog/Todo/2024-05-06-ToDo.md",
                "collapseAll": false,
                "extraContext": false,
                "sortOrder": "alphabetical",
                "showSearch": false,
                "searchQuery": "",
                "backlinkCollapsed": false,
                "unlinkedCollapsed": true
              }
            }
          },
          {
            "id": "769cb969e7defa3e",
            "type": "leaf",
            "state": {
              "type": "outgoing-link",
              "state": {
                "file": "_posts/Blog/Todo/2024-05-06-ToDo.md",
                "linksCollapsed": false,
                "unlinkedCollapsed": true
              }
            }
          },
          {
            "id": "b1e4ca80afc3a8d6",
            "type": "leaf",
            "state": {
              "type": "all-properties",
              "state": {
                "sortOrder": "frequency",
                "showSearch": false,
                "searchQuery": ""
              }
            }
          }
        ]
      }
    ],
    "direction": "horizontal",
    "width": 408.5,
    "collapsed": true
  },
  "left-ribbon": {
    "hiddenItems": {
      "switcher:Open quick switcher": false,
      "graph:Open graph view": false,
      "templates:Insert template": false,
      "command-palette:Open command palette": false,
      "workspaces:Manage workspace layouts": false,
      "obsidian-excalidraw-plugin:Create new drawing": false,
      "table-editor-obsidian:Advanced Tables Toolbar": false
    }
  },
  "active": "c15ca8b08b6f374b",
  "lastOpenFiles": [
    "src/MPC/Trajectory.png",
    "src/MPC/Avoidence.png",
    "src/MPC/Parking.png",
    "src/MPC/Unicycle model.png",
    "_posts/Control/MPC/2024-05-15-Matrix and Vector.md",
    "_posts/Control/MPC/2024-05-21-Optimal control problem.md",
    "src/MPC",
    "_posts/Control/MPC/2024-05-09-Linear-time-invariant-system.md",
    "_posts/Control/MPC/2024-05-07-Matrix and Vector.md",
    "_posts/Blog/Journal/2023-01-15-Confidence is extremely important.md",
    "_posts/Blog/Journal/2023-04-13-My study experience since I came to Japan.md",
    "_posts/Temple/YAML.md",
    "_posts/SystemIdentification/Main/2023-04-10-Linear Continuous-time Model.md",
    "_posts/SystemIdentification/Main/2023-04-20-Continuous time signal sampling.md",
    "_posts/SystemIdentification/Main/2023-05-10-Paramater Estimation for Linear Systems.md",
    "_posts/SystemIdentification/Simulation/2023-04-13-Simulation_Linear discrete-time system model.md",
    "_posts/SystemIdentification/Simulation/2023-04-21-Simulation_Forward differential, backward differential, bilinear transformation.md",
    "_posts/SystemIdentification/Simulation/2023-06-08-Simulation_System Identification.md",
    "_posts/SystemIdentification/Simulation/2023-05-26-Simulation_PID.md",
    "_posts/Blog/2024-04-29-NewBlog.md",
    "_posts/Probability/2024-04-26-Central limit theorem.md",
    "_site/assets/css/jekyll-theme-chirpy.css.map",
    "_posts/Temp/python.md",
    "_posts/Temp/matlab.md",
    "_posts/Probability/2024-05-03-Probability Distributions.md",
    "_posts/Temp/YAML.md",
    "_site/tags/python/index.html",
    "_site/tags/python",
    "_site/tags/probability/index.html",
    "_site/tags/probability",
    "_site/categories/probability/index.html",
    "_site/categories/probability",
    "_site/posts/Probability-Distributions/index.html",
    "_site/posts/Probability-Distributions",
    "_posts/SystemIdentification/Simulation/2023-04-21-Simulation (2).md",
    "_posts/SystemIdentification/Simulation/2023-05-26-Simulation (3)PID.md",
    "_posts/Blog/2024-05-02-Writing.md",
    "README.md",
    "_posts/Temp/Math.md",
    "SystemIdentification/src/20230529165242.png",
    "SystemIdentification/src/20230529164150.png",
    "SystemIdentification/src/20230529145655.png",
    "SystemIdentification/src/20230526101850.png",
    "SystemIdentification/src/20230519160027.png",
    "SystemIdentification/src/20230421184254.png",
    "SystemIdentification/src/20230421140751.png",
    "Untitled.canvas"
  ]
}