{
  "main": {
    "id": "c62e599a04601b4d",
    "type": "split",
    "children": [
      {
        "id": "2ded25ac7279f695",
        "type": "tabs",
        "children": [
          {
            "id": "ae8e07982160d207",
            "type": "leaf",
            "state": {
              "type": "empty",
              "state": {}
            }
          }
        ]
      }
    ],
    "direction": "vertical"
  },
  "left": {
    "id": "699873e72a36232f",
    "type": "split",
    "children": [
      {
        "id": "95e2c06c5fb4ec9e",
        "type": "tabs",
        "children": [
          {
            "id": "193004c8919e2383",
            "type": "leaf",
            "state": {
              "type": "recent-files",
              "state": {}
            }
          },
          {
            "id": "7a96a7b6ca269dce",
            "type": "leaf",
            "state": {
              "type": "file-explorer",
              "state": {
                "sortOrder": "alphabetical"
              }
            }
          },
          {
            "id": "47175694c91b20be",
            "type": "leaf",
            "state": {
              "type": "search",
              "state": {
                "query": "逆行列",
                "matchingCase": false,
                "explainSearch": false,
                "collapseAll": false,
                "extraContext": false,
                "sortOrder": "alphabetical"
              }
            }
          },
          {
            "id": "4e2bd817cc223591",
            "type": "leaf",
            "state": {
              "type": "bookmarks",
              "state": {}
            }
          }
        ],
        "currentTab": 1
      }
    ],
    "direction": "horizontal",
    "width": 335.5
  },
  "right": {
    "id": "c28fa44957b113d7",
    "type": "split",
    "children": [
      {
        "id": "06f2c44063a449fa",
        "type": "tabs",
        "children": [
          {
            "id": "c00359485fd6c205",
            "type": "leaf",
            "state": {
              "type": "outline",
              "state": {}
            }
          },
          {
            "id": "d299e6c63c1dc844",
            "type": "leaf",
            "state": {
              "type": "tag",
              "state": {
                "sortOrder": "frequency",
                "useHierarchy": true
              }
            }
          },
          {
            "id": "3ad40938a2f29454",
            "type": "leaf",
            "state": {
              "type": "calendar",
              "state": {}
            }
          },
          {
            "id": "c86536808d07252c",
            "type": "leaf",
            "state": {
              "type": "backlink",
              "state": {
                "collapseAll": false,
                "extraContext": false,
                "sortOrder": "alphabetical",
                "showSearch": false,
                "searchQuery": "",
                "backlinkCollapsed": false,
                "unlinkedCollapsed": true
              }
            }
          },
          {
            "id": "769cb969e7defa3e",
            "type": "leaf",
            "state": {
              "type": "outgoing-link",
              "state": {
                "linksCollapsed": false,
                "unlinkedCollapsed": true
              }
            }
          },
          {
            "id": "b1e4ca80afc3a8d6",
            "type": "leaf",
            "state": {
              "type": "all-properties",
              "state": {
                "sortOrder": "frequency",
                "showSearch": false,
                "searchQuery": ""
              }
            }
          },
          {
            "id": "ee8a446b5ec9d86b",
            "type": "leaf",
            "state": {
              "type": "timeline",
              "state": {}
            }
          }
        ]
      }
    ],
    "direction": "horizontal",
    "width": 408.5,
    "collapsed": true
  },
  "left-ribbon": {
    "hiddenItems": {
      "switcher:Open quick switcher": false,
      "obsidian-excalidraw-plugin:Create new drawing": false,
      "graph:Open graph view": false,
      "canvas:Create new canvas": false,
      "templates:Insert template": false,
      "command-palette:Open command palette": false,
      "workspaces:Manage workspace layouts": false,
      "webpage-html-export:Export Vault to HTML": false,
      "table-editor-obsidian:Advanced Tables Toolbar": false,
      "obsidian-day-planner:Timeline": false
    }
  },
  "active": "ae8e07982160d207",
  "lastOpenFiles": [
    "Post Temple.md",
    "SystemIdentification/宿題/2023-05-02-3.md",
    "SystemIdentification/宿題/2023-05-09-4.md",
    "SystemIdentification/宿題/2023-04-29-2.md",
    "SystemIdentification/宿題/2023-04-27-1.md",
    "SystemIdentification/子ページ/離散ステップ信号.md",
    "SystemIdentification/子ページ/後退差分.md",
    "SystemIdentification/子ページ/周期関数.md",
    "SystemIdentification/子ページ/伍德伯里矩阵恒等式.md",
    "SystemIdentification/子ページ/前進差分.md",
    "SystemIdentification/子ページ/ヘビサイドの公式.md",
    "SystemIdentification/子ページ/デルタ関数のフーリエ変換.md",
    "SystemIdentification/子ページ/インパルス応答.md",
    "SystemIdentification/子ページ/semi262-PID.pdf",
    "SystemIdentification/子ページ/サンプリング関数.md",
    "SystemIdentification/宿題",
    "SystemIdentification/子ページ",
    "SystemIdentification/3.線形システムのパラメータ推定.md",
    "SystemIdentification/2.サンプリングとz変換.md",
    "SystemIdentification/2023-05-01-Linear Continuous-time Model.md",
    "SystemIdentification",
    "System Identification/2023-05-01-Linear Continuous-time Model.md",
    "System Identification/2023-05-01-1.md",
    "System Identification/宿題/2023-04-27-1.md",
    "System Identification/宿題/2023-04-29-2.md",
    "System Identification/宿題/2023-04-23-Step response of electrical circuits.md",
    "System Identification/宿題/2023-04-23-1.md",
    "System Identification/宿題/2023-04-27-2.md",
    "System Identification/宿題/2023-05-02-3.md",
    "System Identification/宿題/2023-05-09-4.md",
    "System Identification/src/20230407124106.png",
    "System Identification/子ページ/semi262-PID.pdf",
    "System Identification/宿題",
    "System Identification/子ページ",
    "System Identification/src/20230529165242.png",
    "System Identification/src/20230529164150.png",
    "System Identification/src/20230529145655.png",
    "System Identification/src/20230526101850.png",
    "System Identification/src/20230519160027.png",
    "System Identification/src/20230421184254.png",
    "System Identification/src/20230421140751.png",
    "System Identification/src/20230421135821.png",
    "System Identification/src/20230421135456.jpg",
    "System Identification/src",
    "System Identification",
    "Control Engineering/Modeling/Kinematic Bicycle Model — Algorithms for Automated Driving.pdf",
    "Untitled.canvas"
  ]
}